throwbin/PasteModel.py
throwbin/__init__.py
throwbin/constants.py
throwbin/exceptions.py
throwbin-0.1.dist-info/LICENSE
throwbin-0.1.dist-info/METADATA
throwbin-0.1.dist-info/WHEEL
throwbin-0.1.dist-info/top_level.txt
throwbin-0.1.dist-info/RECORD
