Metadata-Version: 2.1
Name: throwbin
Version: 0.1
Summary: API Wrapper for throwbin.io
Home-page: https://github.com/triedgriefdev/throwbin
Author: TriedGriefDev
License: UNKNOWN
Platform: UNKNOWN
Requires-Dist: requests
